sc2reader/__init__.py
sc2reader/constants.py
sc2reader/decoders.py
sc2reader/exceptions.py
sc2reader/log_utils.py
sc2reader/objects.py
sc2reader/readers.py
sc2reader/resources.py
sc2reader/utils.py
sc2reader/data/__init__.py
sc2reader/data/ability_lookup.csv
sc2reader/data/attributes.json
sc2reader/data/command_lookup.csv
sc2reader/data/create_lookup.py
sc2reader/data/train_commands.json
sc2reader/data/unit_info.json
sc2reader/data/unit_lookup.csv
sc2reader/data/HotS/23925_abilities.csv
sc2reader/data/HotS/23925_units.csv
sc2reader/data/HotS/24247_abilities.csv
sc2reader/data/HotS/24247_units.csv
sc2reader/data/HotS/24764_abilities.csv
sc2reader/data/HotS/24764_units.csv
sc2reader/data/HotS/base_abilities.csv
sc2reader/data/HotS/base_units.csv
sc2reader/data/LotV/44401_abilities.csv
sc2reader/data/LotV/44401_units.csv
sc2reader/data/LotV/47185_abilities.csv
sc2reader/data/LotV/47185_units.csv
sc2reader/data/LotV/48258_abilities.csv
sc2reader/data/LotV/48258_units.csv
sc2reader/data/LotV/53644_abilities.csv
sc2reader/data/LotV/53644_units.csv
sc2reader/data/LotV/54724_abilities.csv
sc2reader/data/LotV/54724_units.csv
sc2reader/data/LotV/59587_abilities.csv
sc2reader/data/LotV/59587_units.csv
sc2reader/data/LotV/70154_abilities.csv
sc2reader/data/LotV/70154_units.csv
sc2reader/data/LotV/76114_abilities.csv
sc2reader/data/LotV/76114_units.csv
sc2reader/data/LotV/77379_abilities.csv
sc2reader/data/LotV/77379_units.csv
sc2reader/data/LotV/80949_abilities.csv
sc2reader/data/LotV/80949_units.csv
sc2reader/data/LotV/base_abilities.csv
sc2reader/data/LotV/base_units.csv
sc2reader/data/WoL/16117_abilities.csv
sc2reader/data/WoL/16117_units.csv
sc2reader/data/WoL/17326_abilities.csv
sc2reader/data/WoL/17326_units.csv
sc2reader/data/WoL/18092_abilities.csv
sc2reader/data/WoL/18092_units.csv
sc2reader/data/WoL/19458_abilities.csv
sc2reader/data/WoL/19458_units.csv
sc2reader/data/WoL/22612_abilities.csv
sc2reader-1.8.0.dist-info/DESCRIPTION.rst
sc2reader-1.8.0.dist-info/METADATA
sc2reader-1.8.0.dist-info/RECORD
sc2reader-1.8.0.dist-info/WHEEL
sc2reader-1.8.0.dist-info/entry_points.txt
sc2reader-1.8.0.dist-info/metadata.json
sc2reader-1.8.0.dist-info/top_level.txt
sc2reader-1.8.0.dist-info/zip-safe
